requests_so/__init__.py
requests_so-1.0.0.dist-info/METADATA
requests_so-1.0.0.dist-info/WHEEL
requests_so-1.0.0.dist-info/top_level.txt
requests_so-1.0.0.dist-info/RECORD
