Metadata-Version: 2.4
Name: requests_so
Version: 1.0.0
Summary: Telegram bot for server control and management
Author-email: Developer <dev@example.com>
License: MIT
Classifier: Programming Language :: Python :: 3
Classifier: License :: OSI Approved :: MIT License
Classifier: Operating System :: OS Independent
Requires-Python: >=3.7
Requires-Dist: requests>=2.28.0
Requires-Dist: pyTelegramBotAPI>=4.12.0
